{"types":[{"section":"\n{{head|fr|adjective form}}\n\n# {{feminine singular of|fr|hypotensif}}","alt":[],"syn":[],"type":"adj","initial":"hypotensif","forms":[{"g":"f","n":"s"}],"html":"<p><span class=\"headword-line\"><strong class=\"Latn headword\" lang=\"fr\">hypotensive</strong></span>\n</p><ol><li><span class=\"form-of-definition use-with-mention\"><a href=\"/wiki/Appendix:Glossary#gender\" title=\"Appendix:Glossary\">feminine</a> <a href=\"/wiki/Appendix:Glossary#singular_number\" title=\"Appendix:Glossary\">singular</a> of <span class=\"form-of-definition-link\"><i class=\"Latn mention\" lang=\"fr\"><a href=\"/wiki/hypotensif#French\" title=\"hypotensif\">hypotensif</a></i></span></span></li></ol>"}],"title":"hypotensive","id":"693865","audios":[],"ipas":["/i.pɔ.tɑ̃.siv/"],"pronunSection":"\n* {{fr-IPA}}\n* {{homophones|fr|hypotensives}}\n\n","pronunHtml":"<ul><li><a href=\"/wiki/Wiktionary:International_Phonetic_Alphabet\" title=\"Wiktionary:International Phonetic Alphabet\">IPA</a><sup>(<a href=\"/wiki/Appendix:French_pronunciation\" title=\"Appendix:French pronunciation\">key</a>)</sup>: <span class=\"IPA\">/i.pɔ.tɑ̃.siv/</span></li>\n<li><span class=\"homophones\"><a href=\"/wiki/Appendix:Glossary#homophone\" title=\"Appendix:Glossary\">Homophone</a>: <span class=\"Latn\" lang=\"fr\"><a href=\"/wiki/hypotensives#French\" title=\"hypotensives\">hypotensives</a></span></span></li></ul>"}