{"types":[{"section":"\n{{fr-noun|f}}\n\n# {{l|en|insouciance}}, [[unconcern]]; [[carelessness]], [[recklessness]]\n\n","alt":[],"syn":[],"type":"noun","forms":[{"g":"f","n":"s"}],"html":"<p><span class=\"headword-line\"><strong class=\"Latn headword\" lang=\"fr\">insouciance</strong>&nbsp;<span class=\"gender\"><abbr title=\"feminine gender\">f</abbr></span> (<i>plural</i> <b class=\"Latn form-of lang-fr p-form-of\" lang=\"fr\"><a href=\"/wiki/insouciances#French\" title=\"insouciances\">insouciances</a></b>)</span>\n</p><ol><li><span class=\"Latn\" lang=\"en\"><a class=\"mw-selflink-fragment\" href=\"#English\">insouciance</a></span>, <a href=\"/wiki/unconcern\" title=\"unconcern\">unconcern</a>; <a href=\"/wiki/carelessness\" title=\"carelessness\">carelessness</a>, <a href=\"/wiki/recklessness\" title=\"recklessness\">recklessness</a></li></ol>","trans":["insouciance, unconcern","carelessness, recklessness","insouciance, unconcern","carelessness, recklessness","insouciance, unconcern","carelessness, recklessness"]}],"title":"insouciance","id":"201126","audios":[],"ipas":["/ɛ̃.su.sjɑ̃s/"],"pronunSection":"\n* {{fr-IPA}}\n* {{rhymes|fr|ɑ̃s|s=3}}\n\n","pronunHtml":"<ul><li><a href=\"/wiki/Wiktionary:International_Phonetic_Alphabet\" title=\"Wiktionary:International Phonetic Alphabet\">IPA</a><sup>(<a href=\"/wiki/Appendix:French_pronunciation\" title=\"Appendix:French pronunciation\">key</a>)</sup>: <span class=\"IPA\">/ɛ̃.su.sjɑ̃s/</span></li>\n<li>Rhymes: <a href=\"/wiki/Rhymes:French/%C9%91%CC%83s\" title=\"Rhymes:French/ɑ̃s\"><span class=\"IPA\">-ɑ̃s</span></a></li></ul>"}