{"types":[{"section":"\n{{head|fr|noun form|g=f}}\n\n# {{plural of|fr|oppresseuse}}","alt":[],"syn":[],"type":"noun","initial":"oppresseuse","forms":[{"g":"f","n":"p"}],"html":"<p><span class=\"headword-line\"><strong class=\"Latn headword\" lang=\"fr\">oppresseuses</strong>&nbsp;<span class=\"gender\"><abbr title=\"feminine gender\">f</abbr></span></span>\n</p><ol><li><span class=\"form-of-definition use-with-mention\"><a href=\"/wiki/Appendix:Glossary#plural_number\" title=\"Appendix:Glossary\">plural</a> of <span class=\"form-of-definition-link\"><i class=\"Latn mention\" lang=\"fr\"><a href=\"/wiki/oppresseuse#French\" title=\"oppresseuse\">oppresseuse</a></i></span></span></li></ol>"}],"title":"oppresseuses","id":"7781206","audios":[],"ipas":[]}