{"types":[{"section":"\n{{fr-verb}}\n\n# to [[feed]] {{gloss|provide with nourishment}}, [[nourish]]\n# to [[nurture]], to [[fuel]]\n# {{lb|fr|pronominal}} to [[eat]], to feed oneself\n\n====Conjugation====\n{{fr-conj-auto}}\n\n====Related terms====\n* {{l|fr|nourrice}}\n* {{l|fr|nourrir son homme}}\n* {{l|fr|nourrisson}}\n* {{l|fr|nourriture}}\n* {{l|fr|nutriment}}\n* {{l|fr|nutrition}}\n\n","alt":[],"syn":[],"type":"verb","forms":[{"mod":"inf","aux":["avoir"],"pronom":true,"impers":false}],"trans":["to nourish","to feed , nourish","to nurture, to fuel","to eat, to feed oneself","to feed , nourish","to nurture, to fuel","to eat, to feed oneself"],"group":2,"conj":[{"mod":"indc","tenses":[{"tense":"pres","forms":[["je nourr","is"],["tu nourr","is"],["il nourr","it"],["nous nourr","issons"],["vous nourr","issez"],["ils nourr","issent"]]},{"tense":"pass-c","forms":[["j'ai nourr","i"],["tu as nourr","i"],["il a nourr","i"],["nous avons nourr","i"],["vous avez nourr","i"],["ils ont nourr","i"]]},{"tense":"impf","forms":[["je nourr","issais"],["tu nourr","issais"],["il nourr","issait"],["nous nourr","issions"],["vous nourr","issiez"],["ils nourr","issaient"]]},{"tense":"pqpf","forms":[["j'avais nourr","i"],["tu avais nourr","i"],["il avait nourr","i"],["nous avions nourr","i"],["vous aviez nourr","i"],["ils avaient nourr","i"]]},{"tense":"pass-s","forms":[["je nourr","is"],["tu nourr","is"],["il nourr","it"],["nous nourr","îmes"],["vous nourr","îtes"],["ils nourr","irent"]]},{"tense":"pass-a","forms":[["j'eus nourr","i"],["tu eus nourr","i"],["il eut nourr","i"],["nous eûmes nourr","i"],["vous eûtes nourr","i"],["ils eurent nourr","i"]]},{"tense":"futr","forms":[["je nourr","irai"],["tu nourr","iras"],["il nourr","ira"],["nous nourr","irons"],["vous nourr","irez"],["ils nourr","iront"]]},{"tense":"futr-a","forms":[["j'aurai nourr","i"],["tu auras nourr","i"],["il aura nourr","i"],["nous aurons nourr","i"],["vous aurez nourr","i"],["ils auront nourr","i"]]}]},{"mod":"subj","tenses":[{"tense":"subj-pr","forms":[["que je nourr","isse"],["que tu nourr","isses"],["qu'il nourr","isse"],["que nous nourr","issions"],["que vous nourr","issiez"],["qu'ils nourr","issent"]]},{"tense":"subj-ps","forms":[["que j'aie nourr","i"],["que tu aies nourr","i"],["qu'il ait nourr","i"],["que nous ayons nourr","i"],["que vous ayez nourr","i"],["qu'ils aient nourr","i"]]},{"tense":"subj-im","forms":[["que je nourr","isse"],["que tu nourr","isses"],["qu'il nourr","ît"],["que nous nourr","issions"],["que vous nourr","issiez"],["qu'ils nourr","issent"]]},{"tense":"subj-pq","forms":[["que j'eusse nourr","i"],["que tu eusses nourr","i"],["qu'il eût nourr","i"],["que nous eussions nourr","i"],["que vous eussiez nourr","i"],["qu'ils eussent nourr","i"]]}]},{"mod":"cond","tenses":[{"tense":"cond-pr","forms":[["je nourr","irais"],["tu nourr","irais"],["il nourr","irait"],["nous nourr","irions"],["vous nourr","iriez"],["ils nourr","iraient"]]},{"tense":"cond-pp","forms":[["j'aurais nourr","i"],["tu aurais nourr","i"],["il aurait nourr","i"],["nous aurions nourr","i"],["vous auriez nourr","i"],["ils auraient nourr","i"]]},{"tense":"cond-pd","forms":[["j'eusse nourr","i"],["tu eusses nourr","i"],["il eût nourr","i"],["nous eussions nourr","i"],["vous eussiez nourr","i"],["ils eussent nourr","i"]]}]},{"mod":"impr","tenses":[{"tense":"impr-pr","forms":[["nourr","is"],["nourr","issons"],["nourr","issez"]]},{"tense":"impr-ps","forms":[["aie nourr","i"],["ayons nourr","i"],["ayez nourr","i"]]}]},{"mod":"part","tenses":[{"tense":"part-pr","forms":[["nourr","issant"]]},{"tense":"part-ps","forms":[["nourr","i"],["nourr","ie"],["nourr","is"],["nourr","ies"],["ayant nourr","i"]]}]},{"mod":"inf","tenses":[{"tense":"inf-pr","forms":[["nourrir"]]},{"tense":"inf-ps","forms":[["avoir nourr","i"]]}]},{"mod":"gern","tenses":[{"tense":"gern-pr","forms":[["en nourr","issant"]]},{"tense":"gern-ps","forms":[["en ayant nourr","i"]]}]}],"preps":[{"rel":"v-tran","prep":"à","ex":"nourrir un enfant à la cuillère, au sein, au biberon; nourrir qqn à ne rien faire"},{"rel":"v-tran","prep":"de","ex":"nourrir les poulets de grains; nourrir son imagination de chimères"}],"tags":["freq","transit"],"html":"<p><span class=\"headword-line\"><strong class=\"Latn headword\" lang=\"fr\">nourrir</strong></span>\n</p><ol><li>to <a href=\"/wiki/feed\" title=\"feed\">feed</a> <span class=\"mention-gloss-paren\">(</span><span class=\"mention-gloss\">provide with nourishment</span><span class=\"mention-gloss-paren\">)</span>, <a href=\"/wiki/nourish\" title=\"nourish\">nourish</a></li>\n<li>to <a href=\"/wiki/nurture\" title=\"nurture\">nurture</a>, to <a href=\"/wiki/fuel\" title=\"fuel\">fuel</a></li>\n<li><span class=\"usage-label-sense\"><span class=\"ib-brac label-brac\">(</span><span class=\"ib-content label-content\"><a href=\"/wiki/Appendix:Glossary#pronominal_verb\" title=\"Appendix:Glossary\">pronominal</a></span><span class=\"ib-brac label-brac\">)</span></span> to <a href=\"/wiki/eat\" title=\"eat\">eat</a>, to feed oneself</li></ol><div class=\"mw-heading mw-heading4\"><h4 id=\"Conjugation\">Conjugation</h4><span class=\"mw-editsection\"><span class=\"mw-editsection-bracket\">[</span><a href=\"/w/index.php?title=nourrir&amp;action=edit&amp;section=5\" title=\"Edit section: Conjugation\"><span>edit</span></a><span class=\"mw-editsection-bracket\">]</span></span></div><div class=\"mw-heading mw-heading4\"><h4 id=\"Related_terms\">Related terms</h4><span class=\"mw-editsection\"><span class=\"mw-editsection-bracket\">[</span><a href=\"/w/index.php?title=nourrir&amp;action=edit&amp;section=6\" title=\"Edit section: Related terms\"><span>edit</span></a><span class=\"mw-editsection-bracket\">]</span></span></div><div class=\"list-switcher-wrapper\"><div class=\"list-switcher\" data-toggle-category=\"derived terms\"><div class=\"term-list columns-bg ul-column-count\" data-column-count=\"2\"><ul><li><span class=\"Latn\" lang=\"fr\"><a href=\"/wiki/nourrice#French\" title=\"nourrice\">nourrice</a></span></li><li><span class=\"Latn\" lang=\"fr\"><a href=\"/wiki/nourrir_son_homme#French\" title=\"nourrir son homme\">nourrir son homme</a></span></li><li><span class=\"Latn\" lang=\"fr\"><a href=\"/wiki/nourrisson#French\" title=\"nourrisson\">nourrisson</a></span></li><li><span class=\"Latn\" lang=\"fr\"><a href=\"/wiki/nourriture#French\" title=\"nourriture\">nourriture</a></span></li><li><span class=\"Latn\" lang=\"fr\"><a href=\"/wiki/nutriment#French\" title=\"nutriment\">nutriment</a></span></li><li><span class=\"Latn\" lang=\"fr\"><a href=\"/wiki/nutrition#French\" title=\"nutrition\">nutrition</a></span></li></ul></div></div></div>"}],"title":"nourrir","id":"477193","audios":[{"name":"Fr-nourrir.ogg","url":"https://upload.wikimedia.org/wikipedia/commons/c/c1/Fr-nourrir.ogg"}],"ipas":["/nu.ʁiʁ/"],"pronunSection":"\n* {{fr-IPA}}\n* {{audio|fr|Fr-nourrir.ogg}}\n\n","pronunHtml":"<ul><li><a href=\"/wiki/Wiktionary:International_Phonetic_Alphabet\" title=\"Wiktionary:International Phonetic Alphabet\">IPA</a><sup>(<a href=\"/wiki/Appendix:French_pronunciation\" title=\"Appendix:French pronunciation\">key</a>)</sup>: <span class=\"IPA\">/nu.ʁiʁ/</span></li>\n<li><style data-mw-deduplicate=\"TemplateStyles:r50165410\">.mw-parser-output .k-player .k-attribution{visibility:hidden}</style><table class=\"audiotable\" style=\"\"><tbody><tr><td>Audio<span class=\"ib-colon qualifier-colon\">:</span></td><td class=\"audiofile\"><span typeof=\"mw:File\"><span><audio id=\"mwe_player_0\" controls=\"\" preload=\"none\" data-mw-tmh=\"\" class=\"mw-file-element\" width=\"175\" style=\"\" data-durationhint=\"2\" data-mwtitle=\"Fr-nourrir.ogg\" data-mwprovider=\"wikimediacommons\"><source src=\"//upload.wikimedia.org/wikipedia/commons/c/c1/Fr-nourrir.ogg\" type=\"audio/ogg; codecs=&quot;vorbis&quot;\" data-width=\"0\" data-height=\"0\"><source src=\"//upload.wikimedia.org/wikipedia/commons/transcoded/c/c1/Fr-nourrir.ogg/Fr-nourrir.ogg.mp3\" type=\"audio/mpeg\" data-transcodekey=\"mp3\" data-width=\"0\" data-height=\"0\"></audio></span></span></td><td class=\"audiometa\" style=\"\">(<a href=\"/wiki/File:Fr-nourrir.ogg\" title=\"File:Fr-nourrir.ogg\">file</a>)</td></tr></tbody></table></li></ul>"}