{"types":[{"section":"\n{{fr-noun|m}}\n\n# [[myna]] / [[mynah]] (bird)\n\n","alt":[],"syn":[],"type":"noun","forms":[{"g":"m","n":"s"}],"html":"<p><span class=\"headword-line\"><strong class=\"Latn headword\" lang=\"fr\">mainate</strong>&nbsp;<span class=\"gender\"><abbr title=\"masculine gender\">m</abbr></span> (<i>plural</i> <b class=\"Latn form-of lang-fr p-form-of\" lang=\"fr\"><a href=\"/wiki/mainates#French\" title=\"mainates\">mainates</a></b>)</span>\n</p><ol><li><a href=\"/wiki/myna\" title=\"myna\">myna</a> / <a href=\"/wiki/mynah\" title=\"mynah\">mynah</a> (bird)</li></ol>","trans":["myna / mynah","myna / mynah"]}],"title":"mainate","id":"3556420","audios":[],"ipas":["/mɛ.nat/","/me.nat/"],"pronunSection":"\n* {{fr-IPA}}\n\n","pronunHtml":"<ul><li><a href=\"/wiki/Wiktionary:International_Phonetic_Alphabet\" title=\"Wiktionary:International Phonetic Alphabet\">IPA</a><sup>(<a href=\"/wiki/Appendix:French_pronunciation\" title=\"Appendix:French pronunciation\">key</a>)</sup>: <span class=\"IPA\">/mɛ.nat/</span> ~ <span class=\"IPA\">/me.nat/</span></li></ul>"}