{"types":[{"section":"\n{{head|fr|adjective form}}\n\n# {{masculine plural of|fr|sacrosaint}}","alt":[],"syn":[],"type":"adj","initial":"sacrosaint","forms":[{"g":"m","n":"p"}],"html":"<p><span class=\"headword-line\"><strong class=\"Latn headword\" lang=\"fr\">sacrosaints</strong></span>\n</p><ol><li><span class=\"form-of-definition use-with-mention\"><a href=\"/wiki/Appendix:Glossary#gender\" title=\"Appendix:Glossary\">masculine</a> <a href=\"/wiki/Appendix:Glossary#plural_number\" title=\"Appendix:Glossary\">plural</a> of <span class=\"form-of-definition-link\"><i class=\"Latn mention\" lang=\"fr\"><a href=\"/wiki/sacrosaint#French\" title=\"sacrosaint\">sacrosaint</a></i></span></span></li></ol>"}],"title":"sacrosaints","id":"5112544","audios":[],"ipas":[]}