{"types":[{"section":"\n{{fr-adj}}\n\n# [[paratelic]]","alt":[],"syn":[],"type":"adj","forms":[{"g":"m","n":"s"},{"g":"f","n":"s"}],"html":"<p><span class=\"headword-line\"><strong class=\"Latn headword\" lang=\"fr\">paratélique</strong> (<i>plural</i> <b class=\"Latn form-of lang-fr p-form-of\" lang=\"fr\"><a href=\"/wiki/parat%C3%A9liques#French\" title=\"paratéliques\">paratéliques</a></b>)</span>\n</p><ol><li><a href=\"/w/index.php?title=paratelic&amp;action=edit&amp;redlink=1\" class=\"new\" title=\"paratelic (page does not exist)\">paratelic</a></li></ol>","trans":["paratelic"]}],"title":"paratélique","id":"4972087","audios":[],"ipas":[]}