{"types":[{"section":"\n{{head|fr|verb form}}\n\n# {{inflection of|fr|tracter||1|s|simple|futr}}\n\n","alt":[],"syn":[],"type":"verb","initial":"tracter","forms":[{"p":"1","n":"s","m":"indc","t":"futr"}],"html":"<p><span class=\"headword-line\"><strong class=\"Latn headword\" lang=\"fr\">tracterai</strong></span>\n</p><ol><li><span class=\"form-of-definition use-with-mention\"><a href=\"/wiki/Appendix:Glossary#first_person\" title=\"Appendix:Glossary\">first-person</a> <a href=\"/wiki/Appendix:Glossary#singular_number\" title=\"Appendix:Glossary\">singular</a> simple <a href=\"/wiki/Appendix:Glossary#future_tense\" title=\"Appendix:Glossary\">future</a> of <span class=\"form-of-definition-link\"><i class=\"Latn mention\" lang=\"fr\"><a href=\"/wiki/tracter#French\" title=\"tracter\">tracter</a></i></span></span></li></ol>"}],"title":"tracterai","id":"1716909","audios":[],"ipas":[]}