{"types":[{"section":"\n{{fr-noun|f}}\n\n# {{lb|fr|figuratively}} a [[drop in the ocean]], a [[drop in the bucket]]","alt":[],"syn":[],"type":"noun","forms":[{"g":"f","n":"s"}],"html":"<p><span class=\"headword-line\"><strong class=\"Latn headword\" lang=\"fr\"><a href=\"/wiki/goutte#French\" title=\"goutte\">goutte</a> <a href=\"/wiki/d%27#French\" title=\"d'\">d'</a><a href=\"/wiki/eau#French\" title=\"eau\">eau</a> <a href=\"/wiki/dans#French\" title=\"dans\">dans</a> <a href=\"/wiki/l%27#French\" title=\"l'\">l'</a><a href=\"/wiki/oc%C3%A9an#French\" title=\"océan\">océan</a></strong>&nbsp;<span class=\"gender\"><abbr title=\"feminine gender\">f</abbr></span> (<i>plural</i> <b class=\"Latn form-of lang-fr p-form-of\" lang=\"fr\"><a href=\"/w/index.php?title=gouttes_d%27eau_dans_l%27oc%C3%A9an&amp;action=edit&amp;redlink=1\" class=\"new\" title=\"gouttes d'eau dans l'océan (page does not exist)\">gouttes d'eau dans l'océan</a></b>)</span>\n</p><ol><li><span class=\"usage-label-sense\"><span class=\"ib-brac label-brac\">(</span><span class=\"ib-content label-content\"><a href=\"/wiki/Appendix:Glossary#figurative\" title=\"Appendix:Glossary\">figuratively</a></span><span class=\"ib-brac label-brac\">)</span></span> a <a href=\"/wiki/drop_in_the_ocean\" title=\"drop in the ocean\">drop in the ocean</a>, a <a href=\"/wiki/drop_in_the_bucket\" title=\"drop in the bucket\">drop in the bucket</a></li></ol>","trans":["a drop in the ocean, a drop in the bucket"]}],"title":"goutte d'eau dans l'océan","id":"7319828","audios":[],"ipas":["/ɡut d‿o dɑ̃ l‿ɔ.se.ɑ̃/"],"pronunSection":"\n* {{fr-IPA}}\n\n","pronunHtml":"<ul><li><a href=\"/wiki/Wiktionary:International_Phonetic_Alphabet\" title=\"Wiktionary:International Phonetic Alphabet\">IPA</a><sup>(<a href=\"/wiki/Appendix:French_pronunciation\" title=\"Appendix:French pronunciation\">key</a>)</sup>: <span class=\"IPA\">/ɡut d‿o dɑ̃ l‿ɔ.se.ɑ̃/</span></li></ul>"}