{"types":[{"section":"\n{{fr-verb}}\n\n# to have a good [[journey]], to have a good [[trip]]\n#: {{uxi|fr|Avez-vous '''fait bon voyage''' ?}}\n\n====Related terms====\n* {{l|fr|bon voyage}}\n\n====See also====\n* {{l|fr|faire bonne route}}","alt":[],"syn":[],"type":"verb","forms":[{"mod":"inf","aux":["avoir"],"pronom":false}],"html":"<p><span class=\"headword-line\"><strong class=\"Latn headword\" lang=\"fr\"><a href=\"/wiki/faire#French\" title=\"faire\">faire</a> <a href=\"/wiki/bon#French\" title=\"bon\">bon</a> <a href=\"/wiki/voyage#French\" title=\"voyage\">voyage</a></strong></span>\n</p><ol><li>to have a good <a href=\"/wiki/journey\" title=\"journey\">journey</a>, to have a good <a href=\"/wiki/trip\" title=\"trip\">trip</a>\n<dl><dd><span class=\"h-usage-example\"><i class=\"Latn mention e-example\" lang=\"fr\">Avez-vous <b>fait bon voyage</b> ?</i> ― <small>(please add an English translation of this usage example)</small></span></dd></dl></li></ol><div class=\"mw-heading mw-heading4\"><h4 id=\"Related_terms\">Related terms</h4><span class=\"mw-editsection\"><span class=\"mw-editsection-bracket\">[</span><a href=\"/w/index.php?title=faire_bon_voyage&amp;action=edit&amp;section=4\" title=\"Edit section: Related terms\"><span>edit</span></a><span class=\"mw-editsection-bracket\">]</span></span></div><ul><li><span class=\"Latn\" lang=\"fr\"><a href=\"/wiki/bon_voyage#French\" title=\"bon voyage\">bon voyage</a></span></li></ul><div class=\"mw-heading mw-heading4\"><h4 id=\"See_also\">See also</h4><span class=\"mw-editsection\"><span class=\"mw-editsection-bracket\">[</span><a href=\"/w/index.php?title=faire_bon_voyage&amp;action=edit&amp;section=5\" title=\"Edit section: See also\"><span>edit</span></a><span class=\"mw-editsection-bracket\">]</span></span></div><ul><li><span class=\"Latn\" lang=\"fr\"><a href=\"/wiki/faire_bonne_route#French\" title=\"faire bonne route\">faire bonne route</a></span></li></ul>","trans":["to have a good journey, to have a good trip"]}],"title":"faire bon voyage","id":"8828025","audios":[],"ipas":["/fɛʁ bɔ̃ vwa.jaʒ/"],"pronunSection":"\n* {{fr-IPA}}\n\n","pronunHtml":"<ul><li><a href=\"/wiki/Wiktionary:International_Phonetic_Alphabet\" title=\"Wiktionary:International Phonetic Alphabet\">IPA</a><sup>(<a href=\"/wiki/Appendix:French_pronunciation\" title=\"Appendix:French pronunciation\">key</a>)</sup>: <span class=\"IPA\">/fɛʁ bɔ̃ vwa.jaʒ/</span></li></ul>"}