{"types":[{"section":"\n{{fr-noun|f}}\n\n# [[disassimilation]]\n\n","alt":[],"syn":[],"type":"noun","forms":[{"g":"f","n":"s"}],"html":"<p><span class=\"headword-line\"><strong class=\"Latn headword\" lang=\"fr\">désassimilation</strong>&nbsp;<span class=\"gender\"><abbr title=\"feminine gender\">f</abbr></span> (<i>plural</i> <b class=\"Latn form-of lang-fr p-form-of\" lang=\"fr\"><a href=\"/w/index.php?title=d%C3%A9sassimilations&amp;action=edit&amp;redlink=1\" class=\"new\" title=\"désassimilations (page does not exist)\">désassimilations</a></b>)</span>\n</p><ol><li><a href=\"/wiki/disassimilation\" title=\"disassimilation\">disassimilation</a></li></ol>","trans":["disassimilation"]}],"title":"désassimilation","id":"8745771","audios":[{"name":"LL-Q150 (fra)-WikiLucas00-désassimilation.wav","url":"https://upload.wikimedia.org/wikipedia/commons/7/77/LL-Q150_%28fra%29-WikiLucas00-d%C3%A9sassimilation.wav"}],"ipas":[],"pronunSection":"\n* {{audio|fr|LL-Q150 (fra)-WikiLucas00-désassimilation.wav}}\n\n","pronunHtml":"<ul><li><style data-mw-deduplicate=\"TemplateStyles:r50165410\">.mw-parser-output .k-player .k-attribution{visibility:hidden}</style><table class=\"audiotable\" style=\"\"><tbody><tr><td>Audio<span class=\"ib-colon qualifier-colon\">:</span></td><td class=\"audiofile\"><span typeof=\"mw:File\"><span><audio id=\"mwe_player_0\" controls=\"\" preload=\"none\" data-mw-tmh=\"\" class=\"mw-file-element\" width=\"175\" style=\"\" data-durationhint=\"2\" data-mwtitle=\"LL-Q150_(fra)-WikiLucas00-désassimilation.wav\" data-mwprovider=\"wikimediacommons\"><source src=\"//upload.wikimedia.org/wikipedia/commons/transcoded/7/77/LL-Q150_%28fra%29-WikiLucas00-d%C3%A9sassimilation.wav/LL-Q150_%28fra%29-WikiLucas00-d%C3%A9sassimilation.wav.ogg\" type=\"audio/ogg; codecs=&quot;vorbis&quot;\" data-transcodekey=\"ogg\" data-width=\"0\" data-height=\"0\"><source src=\"//upload.wikimedia.org/wikipedia/commons/transcoded/7/77/LL-Q150_%28fra%29-WikiLucas00-d%C3%A9sassimilation.wav/LL-Q150_%28fra%29-WikiLucas00-d%C3%A9sassimilation.wav.mp3\" type=\"audio/mpeg\" data-transcodekey=\"mp3\" data-width=\"0\" data-height=\"0\"><source src=\"//upload.wikimedia.org/wikipedia/commons/7/77/LL-Q150_%28fra%29-WikiLucas00-d%C3%A9sassimilation.wav\" type=\"audio/wav\" data-width=\"0\" data-height=\"0\"></audio></span></span></td><td class=\"audiometa\" style=\"\">(<a href=\"/wiki/File:LL-Q150_(fra)-WikiLucas00-d%C3%A9sassimilation.wav\" title=\"File:LL-Q150 (fra)-WikiLucas00-désassimilation.wav\">file</a>)</td></tr></tbody></table></li></ul>"}