{"types":[{"section":"\n{{fr-adj|f=dérégulateuse}}\n\n# [[deregulatory]]","alt":[],"syn":[],"type":"adj","forms":[{"g":"m","n":"s"}],"html":"<p><span class=\"headword-line\"><strong class=\"Latn headword\" lang=\"fr\">dérégulateur</strong> (<i>feminine</i> <b class=\"Latn form-of lang-fr f|s-form-of\" lang=\"fr\"><a href=\"/wiki/d%C3%A9r%C3%A9gulateuse#French\" title=\"dérégulateuse\">dérégulateuse</a></b>, <i>masculine plural</i> <b class=\"Latn form-of lang-fr m|p-form-of\" lang=\"fr\"><a href=\"/wiki/d%C3%A9r%C3%A9gulateurs#French\" title=\"dérégulateurs\">dérégulateurs</a></b>, <i>feminine plural</i> <b class=\"Latn form-of lang-fr f|p-form-of\" lang=\"fr\"><a href=\"/wiki/d%C3%A9r%C3%A9gulateuses#French\" title=\"dérégulateuses\">dérégulateuses</a></b>)</span>\n</p><ol><li><a href=\"/wiki/deregulatory\" title=\"deregulatory\">deregulatory</a></li></ol>","trans":["deregulatory"]}],"title":"dérégulateur","id":"5212925","audios":[],"ipas":[]}