{"types":[{"section":"\n{{fr-noun|m}}\n\n# [[osmoreceptor]]","alt":[],"syn":[],"type":"noun","forms":[{"g":"m","n":"s"}],"html":"<p><span class=\"headword-line\"><strong class=\"Latn headword\" lang=\"fr\">osmorécepteur</strong>&nbsp;<span class=\"gender\"><abbr title=\"masculine gender\">m</abbr></span> (<i>plural</i> <b class=\"Latn form-of lang-fr p-form-of\" lang=\"fr\"><a href=\"/wiki/osmor%C3%A9cepteurs#French\" title=\"osmorécepteurs\">osmorécepteurs</a></b>)</span>\n</p><ol><li><a href=\"/wiki/osmoreceptor\" title=\"osmoreceptor\">osmoreceptor</a></li></ol>","trans":["osmoreceptor","osmoreceptor","osmoreceptor"]}],"title":"osmorécepteur","id":"6421043","audios":[],"ipas":[]}