{"types":[{"section":"\n{{fr-noun|f}}\n\n# [[leishmaniasis]]\n\n","alt":[],"syn":[],"type":"noun","forms":[{"g":"f","n":"s"}],"html":"<p><span class=\"headword-line\"><strong class=\"Latn headword\" lang=\"fr\">leishmanie</strong>&nbsp;<span class=\"gender\"><abbr title=\"feminine gender\">f</abbr></span> (<i>plural</i> <b class=\"Latn form-of lang-fr p-form-of\" lang=\"fr\"><a href=\"/w/index.php?title=leishmanies&amp;action=edit&amp;redlink=1\" class=\"new\" title=\"leishmanies (page does not exist)\">leishmanies</a></b>)</span>\n</p><ol><li><a href=\"/wiki/leishmaniasis\" title=\"leishmaniasis\">leishmaniasis</a></li></ol>","trans":["leishmaniasis","leishmaniasis"]}],"title":"leishmanie","id":"8663172","audios":[],"ipas":[]}