{"types":[{"section":"\n{{fr-noun|mf}}\n\n# [[subsecretary]]\n\n","alt":[],"syn":[],"type":"noun","forms":[{"g":"m","n":"s"},{"g":"f","n":"s"}],"html":"<p><span class=\"headword-line\"><strong class=\"Latn headword\" lang=\"fr\"><a href=\"/wiki/sous#French\" title=\"sous\">sous</a>-<a href=\"/wiki/secr%C3%A9taire#French\" title=\"secrétaire\">secrétaire</a></strong>&nbsp;<span class=\"gender\"><abbr title=\"masculine gender\">m</abbr> or <abbr title=\"feminine gender\">f</abbr></span> (<i>plural</i> <b class=\"Latn form-of lang-fr p-form-of\" lang=\"fr\"><a href=\"/w/index.php?title=sous-secr%C3%A9taires&amp;action=edit&amp;redlink=1\" class=\"new\" title=\"sous-secrétaires (page does not exist)\">sous-secrétaires</a></b>)</span>\n</p><ol><li><a href=\"/wiki/subsecretary\" title=\"subsecretary\">subsecretary</a></li></ol>","trans":["subsecretary","subsecretary"]}],"title":"sous-secrétaire","id":"8767876","audios":[],"ipas":[]}