{"types":[{"section":"\n{{fr-adj}}\n\n# [[sextual]]","alt":[],"syn":[],"type":"adj","forms":[{"g":"m","n":"s"}],"html":"<p><span class=\"headword-line\"><strong class=\"Latn headword\" lang=\"fr\">sextuel</strong> (<i>feminine</i> <b class=\"Latn form-of lang-fr f|s-form-of\" lang=\"fr\"><a href=\"/wiki/sextuelle#French\" title=\"sextuelle\">sextuelle</a></b>, <i>masculine plural</i> <b class=\"Latn form-of lang-fr m|p-form-of\" lang=\"fr\"><a href=\"/wiki/sextuels#French\" title=\"sextuels\">sextuels</a></b>, <i>feminine plural</i> <b class=\"Latn form-of lang-fr f|p-form-of\" lang=\"fr\"><a href=\"/wiki/sextuelles#French\" title=\"sextuelles\">sextuelles</a></b>)</span>\n</p><ol><li><a href=\"/wiki/sextual\" title=\"sextual\">sextual</a></li></ol>","trans":["sextual"]}],"title":"sextuel","id":"6475258","audios":[],"ipas":[]}