{"types":[{"section":"\n{{head|fr|noun form|g=?}}\n\n# {{plural of|fr|sebka}}","alt":[],"syn":[],"type":"noun","initial":"sebka","forms":[],"html":"<p><span class=\"headword-line\"><strong class=\"Latn headword\" lang=\"fr\">sebkas</strong>&nbsp;<span class=\"gender\"><abbr title=\"gender incomplete\">?</abbr></span></span>\n</p><ol><li><span class=\"form-of-definition use-with-mention\"><a href=\"/wiki/Appendix:Glossary#plural_number\" title=\"Appendix:Glossary\">plural</a> of <span class=\"form-of-definition-link\"><i class=\"Latn mention\" lang=\"fr\"><a href=\"/wiki/sebka#French\" title=\"sebka\">sebka</a></i></span></span></li></ol>"}],"title":"sebkas","id":"2440946","audios":[],"ipas":[]}