{"types":[{"section":"\n{{fr-noun|m}}\n\n# {{lb|fr|botany|nocat=1}} {{alternative form of|fr|stramoine|t=[[#English|stramonium]]}}\n\n","alt":["stramoine"],"syn":[],"type":"noun","forms":[{"g":"m","n":"s"}],"html":"<p><span class=\"headword-line\"><strong class=\"Latn headword\" lang=\"fr\">stramonium</strong>&nbsp;<span class=\"gender\"><abbr title=\"masculine gender\">m</abbr></span> (<i>plural</i> <b class=\"Latn form-of lang-fr p-form-of\" lang=\"fr\"><a href=\"/wiki/stramoniums#French\" title=\"stramoniums\">stramoniums</a></b>)</span>\n</p><ol><li><span class=\"usage-label-sense\"><span class=\"ib-brac label-brac\">(</span><span class=\"ib-content label-content\"><a href=\"/wiki/botany\" title=\"botany\">botany</a></span><span class=\"ib-brac label-brac\">)</span></span> <span class=\"form-of-definition use-with-mention\">alternative form of <span class=\"form-of-definition-link\"><i class=\"Latn mention\" lang=\"fr\"><a href=\"/wiki/stramoine#French\" title=\"stramoine\">stramoine</a></i> <span class=\"mention-gloss-paren annotation-paren\">(</span><span class=\"mention-gloss-double-quote\">“</span><span class=\"mention-gloss\"><a href=\"#English\">stramonium</a></span><span class=\"mention-gloss-double-quote\">”</span><span class=\"mention-gloss-paren annotation-paren\">)</span></span></span></li></ol>","trans":["alternative form of stramoine"]}],"title":"stramonium","id":"2140154","audios":[],"ipas":[]}