{"types":[{"section":"\n{{fr-adj}}\n\n# [[parasympathomimetic]]","alt":[],"syn":[],"type":"adj","forms":[{"g":"m","n":"s"},{"g":"f","n":"s"}],"html":"<p><span class=\"headword-line\"><strong class=\"Latn headword\" lang=\"fr\">parasympathicomimétique</strong> (<i>plural</i> <b class=\"Latn form-of lang-fr p-form-of\" lang=\"fr\"><a href=\"/wiki/parasympathicomim%C3%A9tiques#French\" title=\"parasympathicomimétiques\">parasympathicomimétiques</a></b>)</span>\n</p><ol><li><a href=\"/wiki/parasympathomimetic\" title=\"parasympathomimetic\">parasympathomimetic</a></li></ol>","trans":["parasympathomimetic"]}],"title":"parasympathicomimétique","id":"4972069","audios":[],"ipas":[]}