{"types":[{"section":"\n{{head|fr|adjective form}}\n\n# {{masculine plural of|fr|prorogé}}","alt":[],"syn":[],"type":"adj","initial":"prorogé","forms":[{"g":"m","n":"p"}],"html":"<p><span class=\"headword-line\"><strong class=\"Latn headword\" lang=\"fr\">prorogés</strong></span>\n</p><ol><li><span class=\"form-of-definition use-with-mention\"><a href=\"/wiki/Appendix:Glossary#gender\" title=\"Appendix:Glossary\">masculine</a> <a href=\"/wiki/Appendix:Glossary#plural_number\" title=\"Appendix:Glossary\">plural</a> of <span class=\"form-of-definition-link\"><i class=\"Latn mention\" lang=\"fr\"><a href=\"/wiki/prorog%C3%A9#French\" title=\"prorogé\">prorogé</a></i></span></span></li></ol>"}],"title":"prorogés","id":"2444819","audios":[],"ipas":[]}