{"types":[{"section":"\n{{head|fr|adjective form}}\n\n# {{feminine singular of|fr|redissout}}","alt":[],"syn":[],"type":"adj","initial":"redissout","forms":[{"g":"f","n":"s"}],"html":"<p><span class=\"headword-line\"><strong class=\"Latn headword\" lang=\"fr\">redissoute</strong></span>\n</p><ol><li><span class=\"form-of-definition use-with-mention\"><a href=\"/wiki/Appendix:Glossary#gender\" title=\"Appendix:Glossary\">feminine</a> <a href=\"/wiki/Appendix:Glossary#singular_number\" title=\"Appendix:Glossary\">singular</a> of <span class=\"form-of-definition-link\"><i class=\"Latn mention\" lang=\"fr\"><a href=\"/wiki/redissout#French\" title=\"redissout\">redissout</a></i></span></span></li></ol>"}],"title":"redissoute","id":"3605456","audios":[],"ipas":[]}