{"types":[{"section":"\n{{fr-noun|f}}\n\n# [[aunt]]\n#: {{ux|fr|Ma mère et ma '''tante''' sont jumelles.|t=My mother and my '''aunt''' are twins.}}\n# {{lb|fr|pejorative}} [[homosexual]] (man); [[faggot]], [[fag]] (''US''); [[poof]] (''UK'')\n\n====Synonyms====\n* {{l|fr|tata}}\n* {{qualifier|Quebec}} {{l|fr|matante}}\n\n====Derived terms====\n* {{l|fr|si ma tante en avait, on l'appellerait mon oncle}}\n* {{l|fr|tantouze}}\n\n====Descendants====\n{{top2}}\n* {{desc|bor=1|eu|ttantta}}\n* {{desc|bor=1|cim|tånte}}\n* {{desctree|bor=1|da|tante}}\n* {{desctree|bor=1|nl|tante}}\n* {{desctree|bor=1|de|Tante}}\n* {{desc|bor=1|frr|tante}}\n* {{desc|bor=1|oc|tanta}}\n* {{desc|bor=1|ro|tanti}}\n* {{desc|bor=1|sv|tant}}\n* {{desc|bor=1|wym|tant}}\n{{bottom}}\n\n====See also====\n* {{l|fr|oncle}}, {{l|fr|tonton}}\n* {{l|fr|cousin}}, {{l|fr|cousine}}\n\n","alt":[],"syn":[],"type":"noun","forms":[{"g":"f","n":"s"}],"html":"<p><span class=\"headword-line\"><strong class=\"Latn headword\" lang=\"fr\">tante</strong>&nbsp;<span class=\"gender\"><abbr title=\"feminine gender\">f</abbr></span> (<i>plural</i> <b class=\"Latn form-of lang-fr p-form-of\" lang=\"fr\"><a href=\"/wiki/tantes#French\" title=\"tantes\">tantes</a></b>)</span>\n</p><ol><li><a href=\"/wiki/aunt\" title=\"aunt\">aunt</a>\n<dl><dd><div class=\"h-usage-example\"><i class=\"Latn mention e-example\" lang=\"fr\">Ma mère et ma <b>tante</b> sont jumelles.</i><dl><dd><span class=\"e-translation\">My mother and my <b>aunt</b> are twins.</span></dd></dl></div></dd></dl></li>\n<li><span class=\"usage-label-sense\"><span class=\"ib-brac label-brac\">(</span><span class=\"ib-content label-content\"><a href=\"/wiki/derogatory\" title=\"derogatory\">derogatory</a></span><span class=\"ib-brac label-brac\">)</span></span> <a href=\"/wiki/homosexual\" title=\"homosexual\">homosexual</a> (man); <a href=\"/wiki/faggot\" title=\"faggot\">faggot</a>, <a href=\"/wiki/fag\" title=\"fag\">fag</a> (<i>US</i>); <a href=\"/wiki/poof\" title=\"poof\">poof</a> (<i>UK</i>)</li></ol><div class=\"mw-heading mw-heading4\"><h4 id=\"Synonyms_2\">Synonyms</h4><span class=\"mw-editsection\"><span class=\"mw-editsection-bracket\">[</span><a href=\"/w/index.php?title=tante&amp;action=edit&amp;section=29\" title=\"Edit section: Synonyms\"><span>edit</span></a><span class=\"mw-editsection-bracket\">]</span></span></div><ul><li><span class=\"Latn\" lang=\"fr\"><a href=\"/wiki/tata#French\" title=\"tata\">tata</a></span></li>\n<li><span class=\"ib-brac qualifier-brac\">(</span><span class=\"ib-content qualifier-content\">Quebec</span><span class=\"ib-brac qualifier-brac\">)</span> <span class=\"Latn\" lang=\"fr\"><a href=\"/wiki/matante#French\" title=\"matante\">matante</a></span></li></ul><div class=\"mw-heading mw-heading4\"><h4 id=\"Derived_terms_2\">Derived terms</h4><span class=\"mw-editsection\"><span class=\"mw-editsection-bracket\">[</span><a href=\"/w/index.php?title=tante&amp;action=edit&amp;section=30\" title=\"Edit section: Derived terms\"><span>edit</span></a><span class=\"mw-editsection-bracket\">]</span></span></div><ul><li><span class=\"Latn\" lang=\"fr\"><a href=\"/wiki/si_ma_tante_en_avait,_on_l%27appellerait_mon_oncle#French\" title=\"si ma tante en avait, on l'appellerait mon oncle\">si ma tante en avait, on l'appellerait mon oncle</a></span></li>\n<li><span class=\"Latn\" lang=\"fr\"><a href=\"/wiki/tantouze#French\" title=\"tantouze\">tantouze</a></span></li></ul><div class=\"mw-heading mw-heading4\"><h4 id=\"Descendants_3\">Descendants</h4><span class=\"mw-editsection\"><span class=\"mw-editsection-bracket\">[</span><a href=\"/w/index.php?title=tante&amp;action=edit&amp;section=31\" title=\"Edit section: Descendants\"><span>edit</span></a><span class=\"mw-editsection-bracket\">]</span></span></div><div class=\"columns-bg ul-column-count\" data-column-count=\"2\">\n<ul><li><span class=\"desc-arr\" title=\"borrowed\">→</span> Basque: <span class=\"Latn\" lang=\"eu\"><a href=\"/wiki/ttantta#Basque\" title=\"ttantta\">ttantta</a></span><link rel=\"mw-deduplicated-inline-style\" href=\"mw-data:TemplateStyles:r68481116\"></li>\n<li><span class=\"desc-arr\" title=\"borrowed\">→</span> Cimbrian: <span class=\"Latn\" lang=\"cim\"><a href=\"/wiki/t%C3%A5nte#Cimbrian\" title=\"tånte\">tånte</a></span><link rel=\"mw-deduplicated-inline-style\" href=\"mw-data:TemplateStyles:r68481116\"></li>\n<li><span class=\"desc-arr\" title=\"borrowed\">→</span> Danish: <span class=\"Latn\" lang=\"da\"><a class=\"mw-selflink-fragment\" href=\"#Danish\">tante</a></span><ul><li><span class=\"desc-arr\" title=\"borrowed\">→</span> Icelandic: <span class=\"Latn\" lang=\"is\"><a href=\"/wiki/tanta#Icelandic\" title=\"tanta\">tanta</a></span><link rel=\"mw-deduplicated-inline-style\" href=\"mw-data:TemplateStyles:r68481116\"></li></ul></li>\n<li><span class=\"desc-arr\" title=\"borrowed\">→</span> Dutch: <span class=\"Latn\" lang=\"nl\"><a class=\"mw-selflink-fragment\" href=\"#Dutch\">tante</a></span><ul><li>Afrikaans: <span class=\"Latn\" lang=\"af\"><a class=\"mw-selflink-fragment\" href=\"#Afrikaans\">tante</a></span><link rel=\"mw-deduplicated-inline-style\" href=\"mw-data:TemplateStyles:r68481116\"></li><li>Berbice Creole Dutch: <span class=\"Latn\" lang=\"brc\"><a href=\"/wiki/tanti#Berbice_Creole_Dutch\" title=\"tanti\">tanti</a></span><link rel=\"mw-deduplicated-inline-style\" href=\"mw-data:TemplateStyles:r68481116\"></li><li>Skepi Creole Dutch: <span class=\"Latn\" lang=\"skw\"><a href=\"/wiki/tanta#Skepi_Creole_Dutch\" title=\"tanta\">tanta</a></span><link rel=\"mw-deduplicated-inline-style\" href=\"mw-data:TemplateStyles:r68481116\"></li><li><span class=\"desc-arr\" title=\"borrowed\">→</span> Aukan: <span class=\"Latn\" lang=\"djk\"><a href=\"/wiki/tanto#Aukan\" title=\"tanto\">tanto</a></span><link rel=\"mw-deduplicated-inline-style\" href=\"mw-data:TemplateStyles:r68481116\"></li><li><span class=\"desc-arr\" title=\"borrowed\">→</span> Malay: <span class=\"Latn\" lang=\"ms\"><a class=\"mw-selflink-fragment\" href=\"#Malay\">tante</a></span><ul><li>Indonesian: <span class=\"Latn\" lang=\"id\"><a class=\"mw-selflink-fragment\" href=\"#Indonesian\">tante</a></span><link rel=\"mw-deduplicated-inline-style\" href=\"mw-data:TemplateStyles:r68481116\"></li></ul></li><li><span class=\"desc-arr\" title=\"borrowed\">→</span> Papiamentu: <span class=\"Latn\" lang=\"pap\"><a href=\"/wiki/tanchi#Papiamentu\" title=\"tanchi\">tanchi</a></span>, <span class=\"Latn\" lang=\"pap\"><a href=\"/wiki/tanta#Papiamentu\" title=\"tanta\">tanta</a></span><link rel=\"mw-deduplicated-inline-style\" href=\"mw-data:TemplateStyles:r68481116\"></li><li><span class=\"desc-arr\" title=\"borrowed\">→</span> Sranan Tongo: <span class=\"Latn\" lang=\"srn\"><a href=\"/wiki/tanta#Sranan_Tongo\" title=\"tanta\">tanta</a></span><link rel=\"mw-deduplicated-inline-style\" href=\"mw-data:TemplateStyles:r68481116\"><ul><li><span class=\"desc-arr\" title=\"borrowed\">→</span> Caribbean Javanese: <span class=\"Latn\" lang=\"jvn\"><a class=\"mw-selflink-fragment\" href=\"#Caribbean_Javanese\">tante</a></span><link rel=\"mw-deduplicated-inline-style\" href=\"mw-data:TemplateStyles:r68481116\"></li></ul></li></ul></li>\n<li><span class=\"desc-arr\" title=\"borrowed\">→</span> German: <span class=\"Latn\" lang=\"de\"><a href=\"/wiki/Tante#German\" title=\"Tante\">Tante</a></span><ul><li><span class=\"desc-arr\" title=\"borrowed\">→</span> Hungarian: <span class=\"Latn\" lang=\"hu\"><a href=\"/wiki/tanti#Hungarian\" title=\"tanti\">tanti</a></span><link rel=\"mw-deduplicated-inline-style\" href=\"mw-data:TemplateStyles:r68481116\"></li><li><span class=\"desc-arr\" title=\"borrowed\">→</span> Latvian: <span class=\"Latn\" lang=\"lv\"><a class=\"mw-selflink-fragment\" href=\"#Latvian\">tante</a></span><link rel=\"mw-deduplicated-inline-style\" href=\"mw-data:TemplateStyles:r68481116\"></li><li><span class=\"desc-arr\" title=\"borrowed\">→</span> Norwegian Bokmål: <span class=\"Latn\" lang=\"nb\"><a class=\"mw-selflink-fragment\" href=\"#Norwegian_Bokmål\">tante</a></span><link rel=\"mw-deduplicated-inline-style\" href=\"mw-data:TemplateStyles:r68481116\"></li><li><span class=\"desc-arr\" title=\"borrowed\">→</span> Yiddish: <span class=\"Hebr\" lang=\"yi\"><a href=\"/wiki/%D7%98%D7%90%D6%B7%D7%A0%D7%98%D7%A2#Yiddish\" title=\"טאַנטע\">טאַנטע</a></span> <span class=\"mention-gloss-paren annotation-paren\">(</span><span lang=\"yi-Latn\" class=\"tr Latn\">tante</span><span class=\"mention-gloss-paren annotation-paren\">)</span><ul><li><span class=\"desc-arr\" title=\"borrowed\">→</span> English: <span class=\"Latn\" lang=\"en\"><a class=\"mw-selflink-fragment\" href=\"#English\">tante</a></span><link rel=\"mw-deduplicated-inline-style\" href=\"mw-data:TemplateStyles:r68481116\"></li></ul></li></ul></li>\n<li><span class=\"desc-arr\" title=\"borrowed\">→</span> North Frisian: <span class=\"Latn\" lang=\"frr\"><a class=\"mw-selflink-fragment\" href=\"#North_Frisian\">tante</a></span><link rel=\"mw-deduplicated-inline-style\" href=\"mw-data:TemplateStyles:r68481116\"></li>\n<li><span class=\"desc-arr\" title=\"borrowed\">→</span> Occitan: <span class=\"Latn\" lang=\"oc\"><a href=\"/wiki/tanta#Occitan\" title=\"tanta\">tanta</a></span><link rel=\"mw-deduplicated-inline-style\" href=\"mw-data:TemplateStyles:r68481116\"></li>\n<li><span class=\"desc-arr\" title=\"borrowed\">→</span> Romanian: <span class=\"Latn\" lang=\"ro\"><a href=\"/wiki/tanti#Romanian\" title=\"tanti\">tanti</a></span><link rel=\"mw-deduplicated-inline-style\" href=\"mw-data:TemplateStyles:r68481116\"></li>\n<li><span class=\"desc-arr\" title=\"borrowed\">→</span> Swedish: <span class=\"Latn\" lang=\"sv\"><a href=\"/wiki/tant#Swedish\" title=\"tant\">tant</a></span><link rel=\"mw-deduplicated-inline-style\" href=\"mw-data:TemplateStyles:r68481116\"></li>\n<li><span class=\"desc-arr\" title=\"borrowed\">→</span> Vilamovian: <span class=\"Latn\" lang=\"wym\"><a href=\"/wiki/tant#Vilamovian\" title=\"tant\">tant</a></span><link rel=\"mw-deduplicated-inline-style\" href=\"mw-data:TemplateStyles:r68481116\"></li></ul>\n</div><div class=\"mw-heading mw-heading4\"><h4 id=\"See_also\">See also</h4><span class=\"mw-editsection\"><span class=\"mw-editsection-bracket\">[</span><a href=\"/w/index.php?title=tante&amp;action=edit&amp;section=32\" title=\"Edit section: See also\"><span>edit</span></a><span class=\"mw-editsection-bracket\">]</span></span></div><ul><li><span class=\"Latn\" lang=\"fr\"><a href=\"/wiki/oncle#French\" title=\"oncle\">oncle</a></span>, <span class=\"Latn\" lang=\"fr\"><a href=\"/wiki/tonton#French\" title=\"tonton\">tonton</a></span></li>\n<li><span class=\"Latn\" lang=\"fr\"><a href=\"/wiki/cousin#French\" title=\"cousin\">cousin</a></span>, <span class=\"Latn\" lang=\"fr\"><a href=\"/wiki/cousine#French\" title=\"cousine\">cousine</a></span></li></ul>","trans":["aunt","homosexual","faggot, fag","poof"]}],"title":"tante","id":"220828","audios":[{"name":"Fr-tante.ogg","url":"https://upload.wikimedia.org/wikipedia/commons/b/b1/Fr-tante.ogg"},{"name":"LL-Q150 (fra)-Poslovitch-tantes.wav","url":"https://upload.wikimedia.org/wikipedia/commons/a/a4/LL-Q150_%28fra%29-Poslovitch-tantes.wav"}],"ipas":["/tɑ̃t/","/tãt/","/t̪ɑ̃t̪/"],"pronunSection":"\n* {{a|fr|France}} {{fr-IPA}}\n* {{IPA|fr|/tãt/|a=Canada}}\n* {{IPA|fr|/t̪ɑ̃t̪/|a=Switzerland}}\n* {{audio|fr|Fr-tante.ogg|a=France}}\n* {{audio|fr|LL-Q150 (fra)-Poslovitch-tantes.wav}}\n* {{homophones|fr|tantes|tente|tentent|tentes}}\n\n","pronunHtml":"<ul><li><span class=\"usage-label-accent\"><span class=\"ib-brac label-brac\">(</span><span class=\"ib-content label-content\"><a href=\"https://en.wikipedia.org/wiki/French_of_France\" class=\"extiw\" title=\"w:French of France\">France</a></span><span class=\"ib-brac label-brac\">)</span></span> <a href=\"/wiki/Wiktionary:International_Phonetic_Alphabet\" title=\"Wiktionary:International Phonetic Alphabet\">IPA</a><sup>(<a href=\"/wiki/Appendix:French_pronunciation\" title=\"Appendix:French pronunciation\">key</a>)</sup>: <span class=\"IPA\">/tɑ̃t/</span></li>\n<li><span class=\"ib-brac qualifier-brac\">(</span><span class=\"ib-content qualifier-content\"><span class=\"usage-label-accent\"><a href=\"https://en.wikipedia.org/wiki/Canadian_French\" class=\"extiw\" title=\"w:Canadian French\">Canada</a></span></span><span class=\"ib-brac qualifier-brac\">)</span> <a href=\"/wiki/Wiktionary:International_Phonetic_Alphabet\" title=\"Wiktionary:International Phonetic Alphabet\">IPA</a><sup>(<a href=\"/wiki/Appendix:French_pronunciation\" title=\"Appendix:French pronunciation\">key</a>)</sup>: <span class=\"IPA\">/tãt/</span></li>\n<li><span class=\"ib-brac qualifier-brac\">(</span><span class=\"ib-content qualifier-content\"><span class=\"usage-label-accent\"><a href=\"https://en.wikipedia.org/wiki/Swiss_French\" class=\"extiw\" title=\"w:Swiss French\">Switzerland</a></span></span><span class=\"ib-brac qualifier-brac\">)</span> <a href=\"/wiki/Wiktionary:International_Phonetic_Alphabet\" title=\"Wiktionary:International Phonetic Alphabet\">IPA</a><sup>(<a href=\"/wiki/Appendix:French_pronunciation\" title=\"Appendix:French pronunciation\">key</a>)</sup>: <span class=\"IPA\">/t̪ɑ̃t̪/</span></li>\n<li><link rel=\"mw-deduplicated-inline-style\" href=\"mw-data:TemplateStyles:r50165410\"><table class=\"audiotable\" style=\"\"><tbody><tr><td>Audio <span class=\"ib-brac qualifier-brac\">(</span><span class=\"usage-label-accent\"><span class=\"ib-content label-content\"><a href=\"https://en.wikipedia.org/wiki/French_of_France\" class=\"extiw\" title=\"w:French of France\">France</a></span></span><span class=\"ib-brac qualifier-brac\">)</span><span class=\"ib-colon qualifier-colon\">:</span></td><td class=\"audiofile\"><span typeof=\"mw:File\"><span><audio id=\"mwe_player_2\" controls=\"\" preload=\"none\" data-mw-tmh=\"\" class=\"mw-file-element\" width=\"175\" style=\"\" data-durationhint=\"2\" data-mwtitle=\"Fr-tante.ogg\" data-mwprovider=\"wikimediacommons\"><source src=\"//upload.wikimedia.org/wikipedia/commons/b/b1/Fr-tante.ogg\" type=\"audio/ogg; codecs=&quot;vorbis&quot;\" data-width=\"0\" data-height=\"0\"><source src=\"//upload.wikimedia.org/wikipedia/commons/transcoded/b/b1/Fr-tante.ogg/Fr-tante.ogg.mp3\" type=\"audio/mpeg\" data-transcodekey=\"mp3\" data-width=\"0\" data-height=\"0\"></audio></span></span></td><td class=\"audiometa\" style=\"\">(<a href=\"/wiki/File:Fr-tante.ogg\" title=\"File:Fr-tante.ogg\">file</a>)</td></tr></tbody></table></li>\n<li><link rel=\"mw-deduplicated-inline-style\" href=\"mw-data:TemplateStyles:r50165410\"><table class=\"audiotable\" style=\"\"><tbody><tr><td>Audio<span class=\"ib-colon qualifier-colon\">:</span></td><td class=\"audiofile\"><span typeof=\"mw:File\"><span><audio id=\"mwe_player_3\" controls=\"\" preload=\"none\" data-mw-tmh=\"\" class=\"mw-file-element\" width=\"175\" style=\"\" data-durationhint=\"2\" data-mwtitle=\"LL-Q150_(fra)-Poslovitch-tantes.wav\" data-mwprovider=\"wikimediacommons\"><source src=\"//upload.wikimedia.org/wikipedia/commons/transcoded/a/a4/LL-Q150_%28fra%29-Poslovitch-tantes.wav/LL-Q150_%28fra%29-Poslovitch-tantes.wav.ogg\" type=\"audio/ogg; codecs=&quot;vorbis&quot;\" data-transcodekey=\"ogg\" data-width=\"0\" data-height=\"0\"><source src=\"//upload.wikimedia.org/wikipedia/commons/transcoded/a/a4/LL-Q150_%28fra%29-Poslovitch-tantes.wav/LL-Q150_%28fra%29-Poslovitch-tantes.wav.mp3\" type=\"audio/mpeg\" data-transcodekey=\"mp3\" data-width=\"0\" data-height=\"0\"><source src=\"//upload.wikimedia.org/wikipedia/commons/a/a4/LL-Q150_%28fra%29-Poslovitch-tantes.wav\" type=\"audio/wav\" data-width=\"0\" data-height=\"0\"></audio></span></span></td><td class=\"audiometa\" style=\"\">(<a href=\"/wiki/File:LL-Q150_(fra)-Poslovitch-tantes.wav\" title=\"File:LL-Q150 (fra)-Poslovitch-tantes.wav\">file</a>)</td></tr></tbody></table></li>\n<li><span class=\"homophones\"><a href=\"/wiki/Appendix:Glossary#homophone\" title=\"Appendix:Glossary\">Homophones</a>: <span class=\"Latn\" lang=\"fr\"><a href=\"/wiki/tantes#French\" title=\"tantes\">tantes</a></span>, <span class=\"Latn\" lang=\"fr\"><a href=\"/wiki/tente#French\" title=\"tente\">tente</a></span>, <span class=\"Latn\" lang=\"fr\"><a href=\"/wiki/tentent#French\" title=\"tentent\">tentent</a></span>, <span class=\"Latn\" lang=\"fr\"><a href=\"/wiki/tentes#French\" title=\"tentes\">tentes</a></span></span></li></ul>"}