{"types":[{"section":"\n{{fr-adj}}\n\n# {{lb|fr|inorganic chemistry}} [[tellurous]]\n\n====Derived terms====\n* {{l|fr|acide tellureux}}\n\n","alt":[],"syn":[],"type":"adj","forms":[{"g":"m","n":"s"},{"g":"m","n":"p"}],"html":"<p><span class=\"headword-line\"><strong class=\"Latn headword\" lang=\"fr\">tellureux</strong> (<i>feminine</i> <b class=\"Latn form-of lang-fr f|s-form-of\" lang=\"fr\"><a href=\"/wiki/tellureuse#French\" title=\"tellureuse\">tellureuse</a></b>, <i>masculine plural</i> <b class=\"Latn form-of lang-fr m|p-form-of\" lang=\"fr\"><strong class=\"selflink\">tellureux</strong></b>, <i>feminine plural</i> <b class=\"Latn form-of lang-fr f|p-form-of\" lang=\"fr\"><a href=\"/wiki/tellureuses#French\" title=\"tellureuses\">tellureuses</a></b>)</span>\n</p><ol><li><span class=\"usage-label-sense\"><span class=\"ib-brac label-brac\">(</span><span class=\"ib-content label-content\"><a href=\"/wiki/inorganic_chemistry\" title=\"inorganic chemistry\">inorganic chemistry</a></span><span class=\"ib-brac label-brac\">)</span></span> <a href=\"/wiki/tellurous\" title=\"tellurous\">tellurous</a></li></ol><div class=\"mw-heading mw-heading4\"><h4 id=\"Derived_terms\">Derived terms</h4><span class=\"mw-editsection\"><span class=\"mw-editsection-bracket\">[</span><a href=\"/w/index.php?title=tellureux&amp;action=edit&amp;section=4\" title=\"Edit section: Derived terms\"><span>edit</span></a><span class=\"mw-editsection-bracket\">]</span></span></div><ul><li><span class=\"Latn\" lang=\"fr\"><a href=\"/w/index.php?title=acide_tellureux&amp;action=edit&amp;redlink=1\" class=\"new\" title=\"acide tellureux (page does not exist)\">acide tellureux</a></span></li></ul>","trans":["tellurous"]}],"title":"tellureux","id":"6431652","audios":[],"ipas":[]}