{"types":[{"section":"\n{{fr-verb}}\n\n# to [[draw up]], [[write up]], [[make up]], [[whip up]], [[put together]]\n#: {{ux|fr|Un compositeur ou une compositrice est une personne musicienne qui '''élabore''' de la musique.|A composer is a musician who '''writes''' music.}}\n# to [[process]] [[farther]], to [[produce]], to [[develop]], to [[metabolize]]\n#: {{uxi|fr|L'embryon élabore une hormone […]|The embry metabolizes a hormone […]}}\n#: {{uxi|fr|Le cœur possède la puissance première d’élaborer le sang.|The heart has the prime power of processing the blood.}}\n# to [[elaborate]], to [[work out]]\n\n====Conjugation====\n{{fr-conj-auto}}\n\n====Related terms====\n* {{l|fr|élaboration}}\n\n====Descendants====\n* {{desc|ro|elabora|bor=1}}\n\n","alt":[],"syn":[],"type":"verb","forms":[{"mod":"inf","aux":["avoir"],"pronom":true,"impers":false}],"trans":["to elaborate","to draw up, write up, make up, whip up, put together","to process farther, to produce, to develop, to metabolize","to elaborate, to work out"],"group":1,"conj":[{"mod":"indc","tenses":[{"tense":"pres","forms":[["j'élabor","e"],["tu élabor","es"],["il élabor","e"],["nous élabor","ons"],["vous élabor","ez"],["ils élabor","ent"]]},{"tense":"pass-c","forms":[["j'ai élabor","é"],["tu as élabor","é"],["il a élabor","é"],["nous avons élabor","é"],["vous avez élabor","é"],["ils ont élabor","é"]]},{"tense":"impf","forms":[["j'élabor","ais"],["tu élabor","ais"],["il élabor","ait"],["nous élabor","ions"],["vous élabor","iez"],["ils élabor","aient"]]},{"tense":"pqpf","forms":[["j'avais élabor","é"],["tu avais élabor","é"],["il avait élabor","é"],["nous avions élabor","é"],["vous aviez élabor","é"],["ils avaient élabor","é"]]},{"tense":"pass-s","forms":[["j'élabor","ai"],["tu élabor","as"],["il élabor","a"],["nous élabor","âmes"],["vous élabor","âtes"],["ils élabor","èrent"]]},{"tense":"pass-a","forms":[["j'eus élabor","é"],["tu eus élabor","é"],["il eut élabor","é"],["nous eûmes élabor","é"],["vous eûtes élabor","é"],["ils eurent élabor","é"]]},{"tense":"futr","forms":[["j'élabor","erai"],["tu élabor","eras"],["il élabor","era"],["nous élabor","erons"],["vous élabor","erez"],["ils élabor","eront"]]},{"tense":"futr-a","forms":[["j'aurai élabor","é"],["tu auras élabor","é"],["il aura élabor","é"],["nous aurons élabor","é"],["vous aurez élabor","é"],["ils auront élabor","é"]]}]},{"mod":"subj","tenses":[{"tense":"subj-pr","forms":[["que j'élabor","e"],["que tu élabor","es"],["qu'il élabor","e"],["que nous élabor","ions"],["que vous élabor","iez"],["qu'ils élabor","ent"]]},{"tense":"subj-ps","forms":[["que j'aie élabor","é"],["que tu aies élabor","é"],["qu'il ait élabor","é"],["que nous ayons élabor","é"],["que vous ayez élabor","é"],["qu'ils aient élabor","é"]]},{"tense":"subj-im","forms":[["que j'élabor","asse"],["que tu élabor","asses"],["qu'il élabor","ât"],["que nous élabor","assions"],["que vous élabor","assiez"],["qu'ils élabor","assent"]]},{"tense":"subj-pq","forms":[["que j'eusse élabor","é"],["que tu eusses élabor","é"],["qu'il eût élabor","é"],["que nous eussions élabor","é"],["que vous eussiez élabor","é"],["qu'ils eussent élabor","é"]]}]},{"mod":"cond","tenses":[{"tense":"cond-pr","forms":[["j'élabor","erais"],["tu élabor","erais"],["il élabor","erait"],["nous élabor","erions"],["vous élabor","eriez"],["ils élabor","eraient"]]},{"tense":"cond-pp","forms":[["j'aurais élabor","é"],["tu aurais élabor","é"],["il aurait élabor","é"],["nous aurions élabor","é"],["vous auriez élabor","é"],["ils auraient élabor","é"]]},{"tense":"cond-pd","forms":[["j'eusse élabor","é"],["tu eusses élabor","é"],["il eût élabor","é"],["nous eussions élabor","é"],["vous eussiez élabor","é"],["ils eussent élabor","é"]]}]},{"mod":"impr","tenses":[{"tense":"impr-pr","forms":[["élabor","e"],["élabor","ons"],["élabor","ez"]]},{"tense":"impr-ps","forms":[["aie élabor","é"],["ayons élabor","é"],["ayez élabor","é"]]}]},{"mod":"part","tenses":[{"tense":"part-pr","forms":[["élabor","ant"]]},{"tense":"part-ps","forms":[["élabor","é"],["élabor","ée"],["élabor","és"],["élabor","ées"],["ayant élabor","é"]]}]},{"mod":"inf","tenses":[{"tense":"inf-pr","forms":[["élaborer"]]},{"tense":"inf-ps","forms":[["avoir élabor","é"]]}]},{"mod":"gern","tenses":[{"tense":"gern-pr","forms":[["en élabor","ant"]]},{"tense":"gern-ps","forms":[["en ayant élabor","é"]]}]}],"tags":["transit"],"html":"<p><span class=\"headword-line\"><strong class=\"Latn headword\" lang=\"fr\">élaborer</strong></span>\n</p><ol><li>to <a href=\"/wiki/draw_up\" title=\"draw up\">draw up</a>, <a href=\"/wiki/write_up\" title=\"write up\">write up</a>, <a href=\"/wiki/make_up\" title=\"make up\">make up</a>, <a href=\"/wiki/whip_up\" title=\"whip up\">whip up</a>, <a href=\"/wiki/put_together\" title=\"put together\">put together</a>\n<dl><dd><div class=\"h-usage-example\"><i class=\"Latn mention e-example\" lang=\"fr\">Un compositeur ou une compositrice est une personne musicienne qui <b>élabore</b> de la musique.</i><dl><dd><span class=\"e-translation\">A composer is a musician who <b>writes</b> music.</span></dd></dl></div></dd></dl></li>\n<li>to <a href=\"/wiki/process\" title=\"process\">process</a> <a href=\"/wiki/farther\" title=\"farther\">farther</a>, to <a href=\"/wiki/produce\" title=\"produce\">produce</a>, to <a href=\"/wiki/develop\" title=\"develop\">develop</a>, to <a href=\"/wiki/metabolize\" title=\"metabolize\">metabolize</a>\n<dl><dd><span class=\"h-usage-example\"><i class=\"Latn mention e-example\" lang=\"fr\">L'embryon élabore une hormone […]</i> ― <span class=\"e-translation\">The embry metabolizes a hormone […]</span></span></dd>\n<dd><span class=\"h-usage-example\"><i class=\"Latn mention e-example\" lang=\"fr\">Le cœur possède la puissance première d’élaborer le sang.</i> ― <span class=\"e-translation\">The heart has the prime power of processing the blood.</span></span></dd></dl></li>\n<li>to <a href=\"/wiki/elaborate\" title=\"elaborate\">elaborate</a>, to <a href=\"/wiki/work_out\" title=\"work out\">work out</a></li></ol><div class=\"mw-heading mw-heading4\"><h4 id=\"Conjugation\">Conjugation</h4><span class=\"mw-editsection\"><span class=\"mw-editsection-bracket\">[</span><a href=\"/w/index.php?title=%C3%A9laborer&amp;action=edit&amp;section=5\" title=\"Edit section: Conjugation\"><span>edit</span></a><span class=\"mw-editsection-bracket\">]</span></span></div><div class=\"mw-heading mw-heading4\"><h4 id=\"Related_terms\">Related terms</h4><span class=\"mw-editsection\"><span class=\"mw-editsection-bracket\">[</span><a href=\"/w/index.php?title=%C3%A9laborer&amp;action=edit&amp;section=6\" title=\"Edit section: Related terms\"><span>edit</span></a><span class=\"mw-editsection-bracket\">]</span></span></div><ul><li><span class=\"Latn\" lang=\"fr\"><a href=\"/wiki/%C3%A9laboration#French\" title=\"élaboration\">élaboration</a></span></li></ul><div class=\"mw-heading mw-heading4\"><h4 id=\"Descendants\">Descendants</h4><span class=\"mw-editsection\"><span class=\"mw-editsection-bracket\">[</span><a href=\"/w/index.php?title=%C3%A9laborer&amp;action=edit&amp;section=7\" title=\"Edit section: Descendants\"><span>edit</span></a><span class=\"mw-editsection-bracket\">]</span></span></div><ul><li><span class=\"desc-arr\" title=\"borrowed\">→</span> Romanian: <span class=\"Latn\" lang=\"ro\"><a href=\"/wiki/elabora#Romanian\" title=\"elabora\">elabora</a></span><style data-mw-deduplicate=\"TemplateStyles:r68481116\">.mw-parser-output .desc-arr[title]{cursor:help}.mw-parser-output .desc-arr[title=\"uncertain\"]{font-size:.7em;vertical-align:super}</style></li></ul>"}],"title":"élaborer","id":"1574260","audios":[{"name":"LL-Q150 (fra)-Lyokoï-élaborer.wav","url":"https://upload.wikimedia.org/wikipedia/commons/e/ed/LL-Q150_%28fra%29-Lyoko%C3%AF-%C3%A9laborer.wav"}],"ipas":["/e.la.bɔ.ʁe/"],"pronunSection":"\n* {{fr-IPA}}\n* {{audio|fr|LL-Q150 (fra)-Lyokoï-élaborer.wav}}\n\n","pronunHtml":"<ul><li><a href=\"/wiki/Wiktionary:International_Phonetic_Alphabet\" title=\"Wiktionary:International Phonetic Alphabet\">IPA</a><sup>(<a href=\"/wiki/Appendix:French_pronunciation\" title=\"Appendix:French pronunciation\">key</a>)</sup>: <span class=\"IPA\">/e.la.bɔ.ʁe/</span></li>\n<li><style data-mw-deduplicate=\"TemplateStyles:r50165410\">.mw-parser-output .k-player .k-attribution{visibility:hidden}</style><table class=\"audiotable\" style=\"\"><tbody><tr><td>Audio<span class=\"ib-colon qualifier-colon\">:</span></td><td class=\"audiofile\"><span typeof=\"mw:File\"><span><audio id=\"mwe_player_0\" controls=\"\" preload=\"none\" data-mw-tmh=\"\" class=\"mw-file-element\" width=\"175\" style=\"\" data-durationhint=\"2\" data-mwtitle=\"LL-Q150_(fra)-Lyokoï-élaborer.wav\" data-mwprovider=\"wikimediacommons\"><source src=\"//upload.wikimedia.org/wikipedia/commons/transcoded/e/ed/LL-Q150_%28fra%29-Lyoko%C3%AF-%C3%A9laborer.wav/LL-Q150_%28fra%29-Lyoko%C3%AF-%C3%A9laborer.wav.ogg\" type=\"audio/ogg; codecs=&quot;vorbis&quot;\" data-transcodekey=\"ogg\" data-width=\"0\" data-height=\"0\"><source src=\"//upload.wikimedia.org/wikipedia/commons/transcoded/e/ed/LL-Q150_%28fra%29-Lyoko%C3%AF-%C3%A9laborer.wav/LL-Q150_%28fra%29-Lyoko%C3%AF-%C3%A9laborer.wav.mp3\" type=\"audio/mpeg\" data-transcodekey=\"mp3\" data-width=\"0\" data-height=\"0\"><source src=\"//upload.wikimedia.org/wikipedia/commons/e/ed/LL-Q150_%28fra%29-Lyoko%C3%AF-%C3%A9laborer.wav\" type=\"audio/wav\" data-width=\"0\" data-height=\"0\"></audio></span></span></td><td class=\"audiometa\" style=\"\">(<a href=\"/wiki/File:LL-Q150_(fra)-Lyoko%C3%AF-%C3%A9laborer.wav\" title=\"File:LL-Q150 (fra)-Lyokoï-élaborer.wav\">file</a>)</td></tr></tbody></table></li></ul>"}