{"types":[{"section":"\n{{head|fr|verb form}}\n\n# {{inflection of|fr|concocter||1|s|phis}}","alt":[],"syn":[],"type":"verb","initial":"concocter","forms":[{"p":"1","n":"s","m":"indc","t":"pass-s"}],"html":"<p><span class=\"headword-line\"><strong class=\"Latn headword\" lang=\"fr\">concoctai</strong></span>\n</p><ol><li><span class=\"form-of-definition use-with-mention\"><a href=\"/wiki/Appendix:Glossary#first_person\" title=\"Appendix:Glossary\">first-person</a> <a href=\"/wiki/Appendix:Glossary#singular_number\" title=\"Appendix:Glossary\">singular</a> past historic of <span class=\"form-of-definition-link\"><i class=\"Latn mention\" lang=\"fr\"><a href=\"/wiki/concocter#French\" title=\"concocter\">concocter</a></i></span></span></li></ol>"}],"title":"concoctai","id":"3256661","audios":[],"ipas":[],"pronunSection":"\n* {{homophones|fr|concocté|concoctée|concoctées|concocter|concoctés|concoctez}}\n\n","pronunHtml":"<ul><li><span class=\"homophones\"><a href=\"/wiki/Appendix:Glossary#homophone\" title=\"Appendix:Glossary\">Homophones</a>: <span class=\"Latn\" lang=\"fr\"><a href=\"/wiki/concoct%C3%A9#French\" title=\"concocté\">concocté</a></span>, <span class=\"Latn\" lang=\"fr\"><a href=\"/wiki/concoct%C3%A9e#French\" title=\"concoctée\">concoctée</a></span>, <span class=\"Latn\" lang=\"fr\"><a href=\"/wiki/concoct%C3%A9es#French\" title=\"concoctées\">concoctées</a></span>, <span class=\"Latn\" lang=\"fr\"><a href=\"/wiki/concocter#French\" title=\"concocter\">concocter</a></span>, <span class=\"Latn\" lang=\"fr\"><a href=\"/wiki/concoct%C3%A9s#French\" title=\"concoctés\">concoctés</a></span>, <span class=\"Latn\" lang=\"fr\"><a href=\"/wiki/concoctez#French\" title=\"concoctez\">concoctez</a></span></span></li></ul>"}