{"types":[{"section":"\n{{fr-verb}}\n\n# {{lb|fr|transitive}} to [[truck]] {{gloss|transport (goods) by truck}}\n\n====Conjugation====\n{{fr-conj-auto}}\n\n","alt":[],"syn":[],"type":"verb","forms":[{"mod":"inf","aux":["avoir"],"pronom":false,"impers":false}],"trans":["to truck","to truck  by truck)"],"group":1,"conj":[{"mod":"indc","tenses":[{"tense":"pres","forms":[["je camionn","e"],["tu camionn","es"],["il camionn","e"],["nous camionn","ons"],["vous camionn","ez"],["ils camionn","ent"]]},{"tense":"pass-c","forms":[["j'ai camionn","é"],["tu as camionn","é"],["il a camionn","é"],["nous avons camionn","é"],["vous avez camionn","é"],["ils ont camionn","é"]]},{"tense":"impf","forms":[["je camionn","ais"],["tu camionn","ais"],["il camionn","ait"],["nous camionn","ions"],["vous camionn","iez"],["ils camionn","aient"]]},{"tense":"pqpf","forms":[["j'avais camionn","é"],["tu avais camionn","é"],["il avait camionn","é"],["nous avions camionn","é"],["vous aviez camionn","é"],["ils avaient camionn","é"]]},{"tense":"pass-s","forms":[["je camionn","ai"],["tu camionn","as"],["il camionn","a"],["nous camionn","âmes"],["vous camionn","âtes"],["ils camionn","èrent"]]},{"tense":"pass-a","forms":[["j'eus camionn","é"],["tu eus camionn","é"],["il eut camionn","é"],["nous eûmes camionn","é"],["vous eûtes camionn","é"],["ils eurent camionn","é"]]},{"tense":"futr","forms":[["je camionn","erai"],["tu camionn","eras"],["il camionn","era"],["nous camionn","erons"],["vous camionn","erez"],["ils camionn","eront"]]},{"tense":"futr-a","forms":[["j'aurai camionn","é"],["tu auras camionn","é"],["il aura camionn","é"],["nous aurons camionn","é"],["vous aurez camionn","é"],["ils auront camionn","é"]]}]},{"mod":"subj","tenses":[{"tense":"subj-pr","forms":[["que je camionn","e"],["que tu camionn","es"],["qu'il camionn","e"],["que nous camionn","ions"],["que vous camionn","iez"],["qu'ils camionn","ent"]]},{"tense":"subj-ps","forms":[["que j'aie camionn","é"],["que tu aies camionn","é"],["qu'il ait camionn","é"],["que nous ayons camionn","é"],["que vous ayez camionn","é"],["qu'ils aient camionn","é"]]},{"tense":"subj-im","forms":[["que je camionn","asse"],["que tu camionn","asses"],["qu'il camionn","ât"],["que nous camionn","assions"],["que vous camionn","assiez"],["qu'ils camionn","assent"]]},{"tense":"subj-pq","forms":[["que j'eusse camionn","é"],["que tu eusses camionn","é"],["qu'il eût camionn","é"],["que nous eussions camionn","é"],["que vous eussiez camionn","é"],["qu'ils eussent camionn","é"]]}]},{"mod":"cond","tenses":[{"tense":"cond-pr","forms":[["je camionn","erais"],["tu camionn","erais"],["il camionn","erait"],["nous camionn","erions"],["vous camionn","eriez"],["ils camionn","eraient"]]},{"tense":"cond-pp","forms":[["j'aurais camionn","é"],["tu aurais camionn","é"],["il aurait camionn","é"],["nous aurions camionn","é"],["vous auriez camionn","é"],["ils auraient camionn","é"]]},{"tense":"cond-pd","forms":[["j'eusse camionn","é"],["tu eusses camionn","é"],["il eût camionn","é"],["nous eussions camionn","é"],["vous eussiez camionn","é"],["ils eussent camionn","é"]]}]},{"mod":"impr","tenses":[{"tense":"impr-pr","forms":[["camionn","e"],["camionn","ons"],["camionn","ez"]]},{"tense":"impr-ps","forms":[["aie camionn","é"],["ayons camionn","é"],["ayez camionn","é"]]}]},{"mod":"part","tenses":[{"tense":"part-pr","forms":[["camionn","ant"]]},{"tense":"part-ps","forms":[["camionn","é"],["camionn","ée"],["camionn","és"],["camionn","ées"],["ayant camionn","é"]]}]},{"mod":"inf","tenses":[{"tense":"inf-pr","forms":[["camionner"]]},{"tense":"inf-ps","forms":[["avoir camionn","é"]]}]},{"mod":"gern","tenses":[{"tense":"gern-pr","forms":[["en camionn","ant"]]},{"tense":"gern-ps","forms":[["en ayant camionn","é"]]}]}],"tags":["transit"],"html":"<p><span class=\"headword-line\"><strong class=\"Latn headword\" lang=\"fr\">camionner</strong></span>\n</p><ol><li><span class=\"usage-label-sense\"><span class=\"ib-brac label-brac\">(</span><span class=\"ib-content label-content\"><a href=\"/wiki/Appendix:Glossary#transitive\" title=\"Appendix:Glossary\">transitive</a></span><span class=\"ib-brac label-brac\">)</span></span> to <a href=\"/wiki/truck\" title=\"truck\">truck</a> <span class=\"mention-gloss-paren\">(</span><span class=\"mention-gloss\">transport (goods) by truck</span><span class=\"mention-gloss-paren\">)</span></li></ol><div class=\"mw-heading mw-heading4\"><h4 id=\"Conjugation\">Conjugation</h4><span class=\"mw-editsection\"><span class=\"mw-editsection-bracket\">[</span><a href=\"/w/index.php?title=camionner&amp;action=edit&amp;section=5\" title=\"Edit section: Conjugation\"><span>edit</span></a><span class=\"mw-editsection-bracket\">]</span></span></div>"}],"title":"camionner","id":"10007684","audios":[],"ipas":["/ka.mjɔ.ne/"],"pronunSection":"\n* {{fr-IPA}}\n* {{rhymes|fr|e|s=3}}\n\n","pronunHtml":"<ul><li><a href=\"/wiki/Wiktionary:International_Phonetic_Alphabet\" title=\"Wiktionary:International Phonetic Alphabet\">IPA</a><sup>(<a href=\"/wiki/Appendix:French_pronunciation\" title=\"Appendix:French pronunciation\">key</a>)</sup>: <span class=\"IPA\">/ka.mjɔ.ne/</span></li>\n<li>Rhymes: <a href=\"/wiki/Rhymes:French/e\" title=\"Rhymes:French/e\"><span class=\"IPA\">-e</span></a></li></ul>"}