{"types":[{"section":"\n{{fr-noun|f-p}}\n\n# [[student affairs]]\n#: {{coi|fr|vice-recteur aux '''affaires étudiantes'''|}}","alt":[],"syn":[],"type":"noun","forms":[{"g":"f","n":"p"}],"html":"<p><span class=\"headword-line\"><strong class=\"Latn headword\" lang=\"fr\"><a href=\"/wiki/affaires#French\" title=\"affaires\">affaires</a> <a href=\"/wiki/%C3%A9tudiantes#French\" title=\"étudiantes\">étudiantes</a></strong>&nbsp;<span class=\"gender\"><abbr title=\"feminine gender\">f</abbr>&nbsp;<abbr title=\"plural number\">pl</abbr></span> (<i>plural only</i>)</span>\n</p><ol><li><a href=\"/wiki/student_affairs\" title=\"student affairs\">student affairs</a>\n<dl><dd><span class=\"h-usage-example collocation\"><i class=\"Latn mention e-example\" lang=\"fr\">vice-recteur aux <b>affaires étudiantes</b></i> ― <small>(please add an English translation of this usage example)</small></span></dd></dl></li></ol>","trans":["student affairs"]}],"title":"affaires étudiantes","id":"10501906","audios":[],"ipas":["/a.fɛ.ʁ‿e.ty.djɑ̃t/","/a.fɛʁ.z‿e.ty.djɑ̃t/"],"pronunSection":"\n* {{fr-IPA|affaire‿étudiantes|affaires‿étudiantes|noalternatives=1}}\n\n","pronunHtml":"<ul><li><a href=\"/wiki/Wiktionary:International_Phonetic_Alphabet\" title=\"Wiktionary:International Phonetic Alphabet\">IPA</a><sup>(<a href=\"/wiki/Appendix:French_pronunciation\" title=\"Appendix:French pronunciation\">key</a>)</sup>: <span class=\"IPA\">/a.fɛ.ʁ‿e.ty.djɑ̃t/</span>, <span class=\"IPA\">/a.fɛʁ.z‿e.ty.djɑ̃t/</span></li></ul>"}