{"types":[{"section":"\n{{fr-noun|m}}\n\n# [[dihedron]]\n\n","alt":[],"syn":[],"type":"noun","forms":[{"g":"m","n":"s"}],"html":"<p><span class=\"headword-line\"><strong class=\"Latn headword\" lang=\"fr\">dièdre</strong>&nbsp;<span class=\"gender\"><abbr title=\"masculine gender\">m</abbr></span> (<i>plural</i> <b class=\"Latn form-of lang-fr p-form-of\" lang=\"fr\"><a href=\"/wiki/di%C3%A8dres#French\" title=\"dièdres\">dièdres</a></b>)</span>\n</p><ol><li><a href=\"/wiki/dihedron\" title=\"dihedron\">dihedron</a></li></ol>","trans":["dihedron"]}],"title":"dièdre","id":"2457117","audios":[],"ipas":[]}