{"types":[{"section":"\n{{fr-adj}}\n\n# {{lb|fr|informal}} [[clever]], [[smart]], [[brainy]]\n\n","alt":[],"syn":[],"type":"adj","forms":[{"g":"m","n":"s"},{"g":"f","n":"s"}],"html":"<p><span class=\"headword-line\"><strong class=\"Latn headword\" lang=\"fr\">fortiche</strong> (<i>plural</i> <b class=\"Latn form-of lang-fr p-form-of\" lang=\"fr\"><a href=\"/wiki/fortiches#French\" title=\"fortiches\">fortiches</a></b>)</span>\n</p><ol><li><span class=\"usage-label-sense\"><span class=\"ib-brac label-brac\">(</span><span class=\"ib-content label-content\"><a href=\"/wiki/Appendix:Glossary#informal\" title=\"Appendix:Glossary\">informal</a></span><span class=\"ib-brac label-brac\">)</span></span> <a href=\"/wiki/clever\" title=\"clever\">clever</a>, <a href=\"/wiki/smart\" title=\"smart\">smart</a>, <a href=\"/wiki/brainy\" title=\"brainy\">brainy</a></li></ol>","trans":["clever, smart, brainy"]},{"section":"\n{{fr-noun|mfbysense}}\n\n# {{lb|fr|informal}} someone who's [[intelligent]], a [[brain]]\n\n","alt":[],"syn":[],"type":"noun","forms":[{"g":"m","n":"s"},{"g":"f","n":"s"}],"html":"<p><span class=\"headword-line\"><strong class=\"Latn headword\" lang=\"fr\">fortiche</strong>&nbsp;<span class=\"gender\"><abbr title=\"masculine gender\">m</abbr> or <abbr title=\"feminine gender\">f</abbr> <abbr title=\"according to the gender of the referent\">by sense</abbr></span> (<i>plural</i> <b class=\"Latn form-of lang-fr p-form-of\" lang=\"fr\"><a href=\"/wiki/fortiches#French\" title=\"fortiches\">fortiches</a></b>)</span>\n</p><ol><li><span class=\"usage-label-sense\"><span class=\"ib-brac label-brac\">(</span><span class=\"ib-content label-content\"><a href=\"/wiki/Appendix:Glossary#informal\" title=\"Appendix:Glossary\">informal</a></span><span class=\"ib-brac label-brac\">)</span></span> someone who's <a href=\"/wiki/intelligent\" title=\"intelligent\">intelligent</a>, a <a href=\"/wiki/brain\" title=\"brain\">brain</a></li></ol>","trans":["someone who's intelligent, a brain"]}],"title":"fortiche","id":"3173034","audios":[],"ipas":[]}